docxprinter/__init__.py
docxprinter/generator.py
resources/__init__.py
resources/prayer.json
resources/template.docx
songpy_docx_printer-1.0.0.dist-info/METADATA
songpy_docx_printer-1.0.0.dist-info/WHEEL
songpy_docx_printer-1.0.0.dist-info/top_level.txt
songpy_docx_printer-1.0.0.dist-info/RECORD
