Metadata-Version: 2.1
Name: songpy-docx-printer
Version: 1.0.0
Summary: Support package for package songpy, for printing formatted songbooks to docx files
Author: Karol Ważny
Requires-Python: >=3.9
Requires-Dist: songpy
Requires-Dist: python-docx
